joao_marcionilo_cep_weather/__init__.py
joao_marcionilo_cep_weather/estates.py
joao_marcionilo_cep_weather/models.py
joao_marcionilo_cep_weather/server.py
joao_marcionilo_cep_weather/system.py
joao_marcionilo_cep_weather-0.1.1.dist-info/METADATA
joao_marcionilo_cep_weather-0.1.1.dist-info/WHEEL
joao_marcionilo_cep_weather-0.1.1.dist-info/licenses/LICENSE
joao_marcionilo_cep_weather-0.1.1.dist-info/RECORD
