Metadata-Version: 2.4
Name: joao_marcionilo_cep_weather
Version: 0.1.1
Summary: Package to fetch data from an CEP API and scrape weather of a capital in Brazil
Project-URL: Homepage, https://github.com/Joao-Marcionilo/cep_weather
Author-email: João Marcionilo <marcionilojob@gmail.com>
License-File: LICENSE
Classifier: License :: OSI Approved :: MIT License
Classifier: Programming Language :: Python :: 3
Requires-Python: >=3.12
Requires-Dist: fastapi~=0.115.4
Requires-Dist: pydantic~=2.9.2
Requires-Dist: requests~=2.32.3
Requires-Dist: selenium~=4.26.1
Requires-Dist: uvicorn~=0.32.0
